phase-01-rtl-systemverilog/projects/01-basic-rtl/src/mux2to1.sv
module mux2_to_1 (
    input logic A,
    input logic B,
    input logic sel,
    output logic Y

);

    assign Y = sel ? A : B;

endmodule

phase-01-rtl-systemverilog/projects/01-basic-rtl/tb/mux2to1_tb.sv
module mux2_to_1_tb;

    logic A;
    logic B;
    logic sel;
    logic Y;


    mux2_to_1 dut (
        .A(B),
        .B(A),
        .sel(sel),
        .Y(Y)
    );

    initial begin 
        $dumpfile("wave/mux2to1.vcd");
        $dumpvars(0, mux2_to_1_tb);


        A = 0;
        B = 0;
        sel = 0;
        #10;

        $display("A=%b B=%b SEL=%b Y=%b", A, B, sel, Y);

        A = 0;
        B = 0;
        sel = 1;
        #10;

        $display("A=%b B=%b SEL=%b Y=%b", A, B, sel, Y);

        A = 1;
        B = 0;
        sel = 0;
        #10;

        $display("A=%b B=%b SEL=%b Y=%b", A, B, sel, Y);

        A = 1;
        B = 0;
        sel = 1;
        #10;

        $display("A=%b B=%b SEL=%b Y=%b", A, B, sel, Y);


        A = 0;
        B = 1;
        sel = 0;
        #10;

        $display("A=%b B=%b SEL=%b Y=%b", A, B, sel, Y);


        A = 0;
        B = 1;
        sel = 1;
        #10;

        $display("A=%b B=%b SEL=%b Y=%b", A, B, sel, Y);


        A = 1;
        B = 1;
        sel = 0;
        #10;

        $display("A=%b B=%b SEL=%b Y=%b", A, B, sel, Y);


        A = 1;
        B = 1;
        sel = 1;
        #10;

        $display("A=%b B=%b SEL=%b Y=%b", A, B, sel, Y);

        $finish;

    end

endmodule

phase-01-rtl-systemverilog/projects/01-basic-rtl/wave/mux2to1.vcd
$date
	Thu Oct 08 00:53:03 2026
$end
$version
	Icarus Verilog
$end
$timescale
	1s
$end
$scope module mux2_to_1_tb $end
$var wire 1 ! Y $end
$var reg 1 " A $end
$var reg 1 # B $end
$var reg 1 $ sel $end
$scope module dut $end
$var wire 1 # A $end
$var wire 1 " B $end
$var wire 1 $ sel $end
$var wire 1 ! Y $end
$upscope $end
$upscope $end
$enddefinitions $end
#0
$dumpvars
0$
0#
0"
0!
$end
#10
1$
#20
1!
0$
1"
#30
0!
1$
#40
0$
1#
0"
#50
1!
1$
#60
0$
1"
#70
1$
