phase-01-rtl-systemverilog/projects/01-basic-rtl/src/regfile32.sv

module regfile32 (
    input  logic        clk,
    input  logic        RegWrite,

    input  logic [4:0]  ReadAddr1,
    input  logic [4:0]  ReadAddr2,
    input  logic [4:0]  WriteAddr,

    input  logic [31:0] WriteData,

    output logic [31:0] ReadData1,
    output logic [31:0] ReadData2
);

    logic [31:0] registers [0:31];

    // Write operation: x0 cannot be modified
    always_ff @(posedge clk) begin
        if (RegWrite && (WriteAddr != 5'd0)) begin
            registers[WriteAddr] <= WriteData;
        end
    end

    // Read operation: x0 always returns zero
    always_comb begin
        if (ReadAddr1 == 5'd0)
            ReadData1 = 32'b0;
        else
            ReadData1 = registers[ReadAddr1];

        if (ReadAddr2 == 5'd0)
            ReadData2 = 32'b0;
        else
            ReadData2 = registers[ReadAddr2];
    end

endmodule

phase-01-rtl-systemverilog/projects/01-basic-rtl/tb/regfile32_tb.sv

`timescale 1ns/1ps

module regfile32_tb;

    logic clk;
    logic RegWrite;

    logic [4:0] ReadAddr1;
    logic [4:0] ReadAddr2;
    logic [4:0] WriteAddr;

    logic [31:0] WriteData;
    logic [31:0] ReadData1;
    logic [31:0] ReadData2;

    // Instantiate the register file
    regfile32 uut (
        .clk(clk),
        .RegWrite(RegWrite),
        .ReadAddr1(ReadAddr1),
        .ReadAddr2(ReadAddr2),
        .WriteAddr(WriteAddr),
        .WriteData(WriteData),
        .ReadData1(ReadData1),
        .ReadData2(ReadData2)
    );

    // 10 ns clock period
    always #5 clk = ~clk;

    initial begin
        clk = 0;
        RegWrite = 0;

        ReadAddr1 = 0;
        ReadAddr2 = 0;
        WriteAddr = 0;
        WriteData = 0;

        $dumpfile("wave/regfile32.vcd");
        $dumpvars(0, regfile32_tb);

        // Test 1: Write 100 into register 5
        @(negedge clk);
        RegWrite = 1;
        WriteAddr = 5;
        WriteData = 100;

        @(posedge clk);
        #1;
        ReadAddr1 = 5;
        #1;
        $display("Test 1: R5=%0d", ReadData1);

        // Test 2: Write 200 into register 10
        @(negedge clk);
        WriteAddr = 10;
        WriteData = 200;

        @(posedge clk);
        #1;
        ReadAddr1 = 5;
        ReadAddr2 = 10;
        #1;
        $display("Test 2: R5=%0d R10=%0d",
                 ReadData1, ReadData2);

        // Test 3: Disable writes and try to overwrite R5
        @(negedge clk);
        RegWrite = 0;
        WriteAddr = 5;
        WriteData = 999;

        @(posedge clk);
        #1;
        ReadAddr1 = 5;
        ReadAddr2 = 10;
        #1;
        $display("Test 3: R5=%0d R10=%0d",
                 ReadData1, ReadData2);

        // Test 4: Write 1234 into register 31
        @(negedge clk);
        RegWrite = 1;
        WriteAddr = 31;
        WriteData = 1234;

        @(posedge clk);
        #1;
        ReadAddr1 = 31;
        ReadAddr2 = 10;
        #1;
        $display("Test 4: R31=%0d R10=%0d",
                 ReadData1, ReadData2);


         // Test 5: Attempt to write 999 into x0
        @(negedge clk);
        RegWrite = 1;
        WriteAddr = 0;
        WriteData = 999;

        @(posedge clk);
        #1;
        ReadAddr1 = 0;
        #1;
        $display("Test 5: x0=%0d (expected 0)", ReadData1);

        // Test 6: Read x0 and a normal register
        ReadAddr1 = 0;
        ReadAddr2 = 5;
        #1;
        $display("Test 6: x0=%0d R5=%0d",
                 ReadData1, ReadData2);

        $finish;
    end

endmodule

phase-01-rtl-systemverilog/projects/01-basic-rtl/wave/regfile32.vcd
$date
	Sat Oct 10 03:40:23 2026
$end
$version
	Icarus Verilog
$end
$timescale
	1ps
$end
$scope module regfile32_tb $end
$var wire 32 ! ReadData2 [31:0] $end
$var wire 32 " ReadData1 [31:0] $end
$var reg 5 # ReadAddr1 [4:0] $end
$var reg 5 $ ReadAddr2 [4:0] $end
$var reg 1 % RegWrite $end
$var reg 5 & WriteAddr [4:0] $end
$var reg 32 ' WriteData [31:0] $end
$var reg 1 ( clk $end
$scope module uut $end
$var wire 5 ) ReadAddr1 [4:0] $end
$var wire 5 * ReadAddr2 [4:0] $end
$var wire 1 % RegWrite $end
$var wire 5 + WriteAddr [4:0] $end
$var wire 32 , WriteData [31:0] $end
$var wire 1 ( clk $end
$var reg 32 - ReadData1 [31:0] $end
$var reg 32 . ReadData2 [31:0] $end
$upscope $end
$upscope $end
$enddefinitions $end
#0
$dumpvars
b0 .
b0 -
b0 ,
b0 +
b0 *
b0 )
0(
b0 '
b0 &
0%
b0 $
b0 #
b0 "
b0 !
$end
#5000
1(
#10000
b1100100 '
b1100100 ,
b101 &
b101 +
1%
0(
#15000
1(
#16000
b1100100 "
b1100100 -
b101 #
b101 )
#20000
b11001000 '
b11001000 ,
b1010 &
b1010 +
0(
#25000
1(
#26000
b11001000 !
b11001000 .
b1010 $
b1010 *
#30000
b1111100111 '
b1111100111 ,
b101 &
b101 +
0%
0(
#35000
1(
#40000
b10011010010 '
b10011010010 ,
b11111 &
b11111 +
1%
0(
#45000
1(
#46000
b10011010010 "
b10011010010 -
b11111 #
b11111 )
#50000
b1111100111 '
b1111100111 ,
b0 &
b0 +
0(
#55000
1(
#56000
b0 "
b0 -
b0 #
b0 )
#57000
b1100100 !
b1100100 .
b101 $
b101 *
